NiukeChanpinJingliMianshiZhentiBaodian20212022Fix1/README.md
NiukeChanpinJingliMianshiZhentiBaodian20212022Fix1/__init__.py
NiukeChanpinJingliMianshiZhentiBaodian20212022Fix1/__main__.py
NiukeChanpinJingliMianshiZhentiBaodian20212022Fix1/file.epub
NiukeChanpinJingliMianshiZhentiBaodian20212022Fix1/index.html
NiukeChanpinJingliMianshiZhentiBaodian20212022Fix1/css/__init__.py
NiukeChanpinJingliMianshiZhentiBaodian20212022Fix1/css/annotations.css
NiukeChanpinJingliMianshiZhentiBaodian20212022Fix1/css/main.css
NiukeChanpinJingliMianshiZhentiBaodian20212022Fix1/css/normalize.css
NiukeChanpinJingliMianshiZhentiBaodian20212022Fix1/css/popup.css
NiukeChanpinJingliMianshiZhentiBaodian20212022Fix1/font/__init__.py
NiukeChanpinJingliMianshiZhentiBaodian20212022Fix1/font/fontello.eot
NiukeChanpinJingliMianshiZhentiBaodian20212022Fix1/font/fontello.svg
NiukeChanpinJingliMianshiZhentiBaodian20212022Fix1/font/fontello.ttf
NiukeChanpinJingliMianshiZhentiBaodian20212022Fix1/font/fontello.woff
NiukeChanpinJingliMianshiZhentiBaodian20212022Fix1/img/__init__.py
NiukeChanpinJingliMianshiZhentiBaodian20212022Fix1/img/annotator-glyph-sprite.png
NiukeChanpinJingliMianshiZhentiBaodian20212022Fix1/img/annotator-icon-sprite.png
NiukeChanpinJingliMianshiZhentiBaodian20212022Fix1/img/apple-touch-icon.png
NiukeChanpinJingliMianshiZhentiBaodian20212022Fix1/img/cancelfullscreen.png
NiukeChanpinJingliMianshiZhentiBaodian20212022Fix1/img/close.png
NiukeChanpinJingliMianshiZhentiBaodian20212022Fix1/img/fullscreen.png
NiukeChanpinJingliMianshiZhentiBaodian20212022Fix1/img/loader.gif
NiukeChanpinJingliMianshiZhentiBaodian20212022Fix1/img/menu-icon.png
NiukeChanpinJingliMianshiZhentiBaodian20212022Fix1/img/save.png
NiukeChanpinJingliMianshiZhentiBaodian20212022Fix1/img/saved.png
NiukeChanpinJingliMianshiZhentiBaodian20212022Fix1/img/settings-s.png
NiukeChanpinJingliMianshiZhentiBaodian20212022Fix1/img/settings.png
NiukeChanpinJingliMianshiZhentiBaodian20212022Fix1/img/star.png
niuke_chanpin_jingli_mianshi_zhenti_baodian_2021_2022_fix1-2025.3.25.0.dist-info/METADATA
niuke_chanpin_jingli_mianshi_zhenti_baodian_2021_2022_fix1-2025.3.25.0.dist-info/WHEEL
niuke_chanpin_jingli_mianshi_zhenti_baodian_2021_2022_fix1-2025.3.25.0.dist-info/entry_points.txt
niuke_chanpin_jingli_mianshi_zhenti_baodian_2021_2022_fix1-2025.3.25.0.dist-info/top_level.txt
niuke_chanpin_jingli_mianshi_zhenti_baodian_2021_2022_fix1-2025.3.25.0.dist-info/RECORD
